struct_parse/__init__.py
struct_parse-0.0.2.dist-info/LICENSE
struct_parse-0.0.2.dist-info/METADATA
struct_parse-0.0.2.dist-info/WHEEL
struct_parse-0.0.2.dist-info/top_level.txt
struct_parse-0.0.2.dist-info/RECORD
