Metadata-Version: 2.1
Name: struct-parse
Version: 0.0.2
Summary: Parse struct definitions like those used in the struct module
Home-page: https://github.com/zmarvel/struct_parse
Author: Zack Marvel
Author-email: zpmarvel@gmail.com
License: MIT
Project-URL: Bug Tracker, https://github.com/zmarvel/struct_parse/issues
Project-URL: Documentation, https://struct-parse.readthedocs.io/
Project-URL: Source Code, https://github.com/zmarvel/struct_parse
Platform: UNKNOWN
Classifier: Programming Language :: Python :: 3
Classifier: License :: OSI Approved :: MIT License
Classifier: Operating System :: OS Independent
Requires-Python: >=3.6
